slixbot/__init__.py
slixbot/client.py
slixbot/e2ee.py
slixbot/entity.py
slixbot/message.py
slixbot/xmpp.py
slixbot-0.1.0a0.dist-info/METADATA
slixbot-0.1.0a0.dist-info/WHEEL
slixbot-0.1.0a0.dist-info/top_level.txt
slixbot-0.1.0a0.dist-info/RECORD
