Metadata-Version: 2.4
Name: slixbot
Version: 0.1.0a0
Summary: Easy library to make XMPP/Jabber bots
Project-URL: Homepage, https://codeberg.org/nicoco/slixbot
Project-URL: Issues, https://codeberg.org/nicoco/slixbot/issues
Project-URL: Repository, https://codeberg.org/nicoco/slixbot
Project-URL: Documentation, https://codeberg.org/nicoco/slixbot
Project-URL: changelog, https://codeberg.org/nicoco/slixbot/releases
Requires-Python: >=3.13
Requires-Dist: slixmpp-omemo<3,>=2
Requires-Dist: slixmpp[xep-0363]<2,>=1.12
